chromewrapper/__init__.py
chromewrapper-0.0.5.dist-info/METADATA
chromewrapper-0.0.5.dist-info/WHEEL
chromewrapper-0.0.5.dist-info/top_level.txt
chromewrapper-0.0.5.dist-info/RECORD
