Metadata-Version: 2.1
Name: chromewrapper
Version: 0.0.5
Summary: Vizio Controller
Home-page: https://github.com/48723247842/ChromeWrapper
Author: 7435171
Author-email: 48723247842@protonmail.com
License: UNKNOWN
Platform: UNKNOWN
Classifier: Programming Language :: Python :: 3
Classifier: License :: OSI Approved :: MIT License
Classifier: Operating System :: OS Independent
Requires-Python: >=3.8
Requires-Dist: XDoToolWrapper (==0.0.3)
